[{"pk": 1, "model": "testapp.testperson", "fields": {"first_name": "acroarthritis inheritor ulcerous", "last_name": "falcata crymodynia fogey"}}, {"pk": 2, "model": "testapp.testperson", "fields": {"first_name": "pipecolinic valvular uncomprehensible", "last_name": "hamingja granitization compendiary"}}, {"pk": 3, "model": "testapp.testperson", "fields": {"first_name": "riddlings uncomplying undeceiver", "last_name": "uredosporic hogherd friedelite"}}, {"pk": 4, "model": "testapp.testperson", "fields": {"first_name": "peritoneoscopy unverbalized plantaginaceae", "last_name": "manifestness undyingness concubitous"}}, {"pk": 5, "model": "testapp.testperson", "fields": {"first_name": "lechwe pishu lichen", "last_name": "impedance standpatism immobilize"}}, {"pk": 6, "model": "testapp.testperson", "fields": {"first_name": "undrinkableness pluriguttulate fluorspar", "last_name": "denominator semierect unmindfulness"}}, {"pk": 7, "model": "testapp.testperson", "fields": {"first_name": "quilling euphorbium trichodesmium", "last_name": "ampangabeite hopperings parietes"}}, {"pk": 8, "model": "testapp.testperson", "fields": {"first_name": "sulpha hippocamp prochurchian", "last_name": "unparroted demodicidae dextrogyrate"}}, {"pk": 9, "model": "testapp.testperson", "fields": {"first_name": "ilmenorutile cliental hysterioid", "last_name": "forbiddal undersleeve nondisqualifying"}}, {"pk": 10, "model": "testapp.testperson", "fields": {"first_name": "hyposphene propine transmissibility", "last_name": "exactment gastrotricha antialexin"}}, {"pk": 11, "model": "testapp.testperson", "fields": {"first_name": "illaudation sparklike crystallochemistry", "last_name": "liesh noumenally mismeasure"}}, {"pk": 12, "model": "testapp.testperson", "fields": {"first_name": "matchless dene unvintaged", "last_name": "carbamic limicolae monarchial"}}, {"pk": 13, "model": "testapp.testperson", "fields": {"first_name": "alhambraic succinimide aegipan", "last_name": "roughings vitellicle copetitioner"}}, {"pk": 14, "model": "testapp.testperson", "fields": {"first_name": "drearfully cetylene unfriarlike", "last_name": "paurometabola discarnate unimpeachably"}}, {"pk": 15, "model": "testapp.testperson", "fields": {"first_name": "peristeronic attask cherimoya", "last_name": "epiglottic whirlgig sanidine"}}, {"pk": 16, "model": "testapp.testperson", "fields": {"first_name": "epidural bifariously archfire", "last_name": "acarida blabber coumarilic"}}, {"pk": 17, "model": "testapp.testperson", "fields": {"first_name": "anapnea hematohidrosis anisomeric", "last_name": "extrapolative mensuralist pinfeathered"}}, {"pk": 18, "model": "testapp.testperson", "fields": {"first_name": "sutlerage megarensian transfuser", "last_name": "nonobservation symbolicly bawn"}}, {"pk": 19, "model": "testapp.testperson", "fields": {"first_name": "venally stakhanovite undramatized", "last_name": "antirationalist magnetooptics unsuppressible"}}, {"pk": 20, "model": "testapp.testperson", "fields": {"first_name": "priestdom outcaper diarchial", "last_name": "wodge parapsis sprinkling"}}, {"pk": 21, "model": "testapp.testperson", "fields": {"first_name": "bicostate hemologist antesunrise", "last_name": "facet energetically woodcut"}}, {"pk": 22, "model": "testapp.testperson", "fields": {"first_name": "planilla rhinal wigwam", "last_name": "zenobia eciton ungovernable"}}, {"pk": 23, "model": "testapp.testperson", "fields": {"first_name": "redeposition ectocornea patriotship", "last_name": "presuffrage cipango arabianize"}}, {"pk": 24, "model": "testapp.testperson", "fields": {"first_name": "uncrowded laborant trinklement", "last_name": "sad prefixion citrometer"}}, {"pk": 25, "model": "testapp.testperson", "fields": {"first_name": "mussably aliveness doctorfish", "last_name": "anthranone hurdleman clothing"}}, {"pk": 26, "model": "testapp.testperson", "fields": {"first_name": "armiferous uncrooking pilosis", "last_name": "paradeful prosternum vibrionic"}}, {"pk": 27, "model": "testapp.testperson", "fields": {"first_name": "moveableness enactor pyrone", "last_name": "autobasidiomycetous unexcelled catullian"}}, {"pk": 28, "model": "testapp.testperson", "fields": {"first_name": "evanescible angiospermae pointrel", "last_name": "helladotherium departition problematic"}}, {"pk": 29, "model": "testapp.testperson", "fields": {"first_name": "belgae rhinanthaceae terrifically", "last_name": "tungus maegbote nonobedience"}}, {"pk": 30, "model": "testapp.testperson", "fields": {"first_name": "circumspect cerebellocortex glumiflorae", "last_name": "pseudoprofessional sensable eudora"}}, {"pk": 31, "model": "testapp.testperson", "fields": {"first_name": "pulish decumbiture fleckiness", "last_name": "articulus irisated katachromasis"}}, {"pk": 32, "model": "testapp.testperson", "fields": {"first_name": "bargelike bairnly lebrancho", "last_name": "thermionics mnemonic trypanosomal"}}, {"pk": 33, "model": "testapp.testperson", "fields": {"first_name": "bloomsbury constitutioner tautophonical", "last_name": "moistful hypericales clootie"}}, {"pk": 34, "model": "testapp.testperson", "fields": {"first_name": "overcut withen triakisoctahedral", "last_name": "dollface voet micromillimeter"}}, {"pk": 35, "model": "testapp.testperson", "fields": {"first_name": "grandiosely tarsale phenylacetaldehyde", "last_name": "veridically atactiform gymnocerata"}}, {"pk": 36, "model": "testapp.testperson", "fields": {"first_name": "anniversarily polyphylline leucorrhea", "last_name": "morinel contrasty antiprotozoal"}}, {"pk": 37, "model": "testapp.testperson", "fields": {"first_name": "presension slommock orolingual", "last_name": "desmoncus nonrevolting unminted"}}, {"pk": 38, "model": "testapp.testperson", "fields": {"first_name": "horologer coffeeleaf serf", "last_name": "illicitness hairpin schizolaenaceous"}}, {"pk": 39, "model": "testapp.testperson", "fields": {"first_name": "bolyaian inveigler ramlike", "last_name": "monocot bandbox salar"}}, {"pk": 40, "model": "testapp.testperson", "fields": {"first_name": "focusable maholi titheless", "last_name": "scruf moundy eighthly"}}, {"pk": 41, "model": "testapp.testperson", "fields": {"first_name": "questman catamiting pansied", "last_name": "crocker insolidity collocative"}}, {"pk": 42, "model": "testapp.testperson", "fields": {"first_name": "careen washtub forenotice", "last_name": "oinochoe liebenerite mollicrush"}}, {"pk": 43, "model": "testapp.testperson", "fields": {"first_name": "convulsant chelonian module", "last_name": "chastiser catechu omnicredulous"}}, {"pk": 44, "model": "testapp.testperson", "fields": {"first_name": "clit pacificatory mowstead", "last_name": "graze sudoriferous trottoired"}}, {"pk": 45, "model": "testapp.testperson", "fields": {"first_name": "drow corneocalcareous affixture", "last_name": "chromolithic minxish epagomenal"}}, {"pk": 46, "model": "testapp.testperson", "fields": {"first_name": "yati streamwort novarsenobenzene", "last_name": "obex perisinuitis polymeric"}}, {"pk": 47, "model": "testapp.testperson", "fields": {"first_name": "unshrinkability kusan nonintention", "last_name": "motionlessness hinderfully bessi"}}, {"pk": 48, "model": "testapp.testperson", "fields": {"first_name": "saxon acanthopteri dagoba", "last_name": "acoelomate postbaptismal pleurotomaria"}}, {"pk": 49, "model": "testapp.testperson", "fields": {"first_name": "colocephalous caupo fangled", "last_name": "unobliging squatmore undersill"}}, {"pk": 50, "model": "testapp.testperson", "fields": {"first_name": "micronization domestically agnoetism", "last_name": "unrevolted spet griffade"}}, {"pk": 51, "model": "testapp.testperson", "fields": {"first_name": "indicable habille myristone", "last_name": "uncling oyster handybook"}}, {"pk": 52, "model": "testapp.testperson", "fields": {"first_name": "ascender grumble coccolithophoridae", "last_name": "gaviae tapa paralogize"}}, {"pk": 53, "model": "testapp.testperson", "fields": {"first_name": "chondroangioma phenacyl repetitiously", "last_name": "stableward unrecreated graduality"}}, {"pk": 54, "model": "testapp.testperson", "fields": {"first_name": "enterable irrecollection coxodynia", "last_name": "bacterium trellis pilotry"}}, {"pk": 55, "model": "testapp.testperson", "fields": {"first_name": "somnolism summist trigonododecahedron", "last_name": "pilotweed bestride forecatching"}}, {"pk": 56, "model": "testapp.testperson", "fields": {"first_name": "apartment cograil carpophagous", "last_name": "outread ponderousness rewind"}}, {"pk": 57, "model": "testapp.testperson", "fields": {"first_name": "unalist freehandedness maladroit", "last_name": "neologist naturalist wench"}}, {"pk": 58, "model": "testapp.testperson", "fields": {"first_name": "baffeta pipecoline traguline", "last_name": "desmatippus tillable thronize"}}, {"pk": 59, "model": "testapp.testperson", "fields": {"first_name": "invidiously cytozoon sweatily", "last_name": "notself elementary lawyership"}}, {"pk": 60, "model": "testapp.testperson", "fields": {"first_name": "vallum reassemble nonvulcanizable", "last_name": "unnobleness aphthartodocetism loather"}}, {"pk": 61, "model": "testapp.testperson", "fields": {"first_name": "jocasta chironomic spile", "last_name": "rubbly catchpenny helmetmaker"}}, {"pk": 62, "model": "testapp.testperson", "fields": {"first_name": "unespoused hulloo reconciliability", "last_name": "carpoptosis monopolizable gradiometer"}}, {"pk": 63, "model": "testapp.testperson", "fields": {"first_name": "horme dorsad mistakably", "last_name": "hypochondrial carnage vinal"}}, {"pk": 64, "model": "testapp.testperson", "fields": {"first_name": "unpleat biplosion schnabelkanne", "last_name": "branchiopulmonate aedoeagus interbank"}}, {"pk": 65, "model": "testapp.testperson", "fields": {"first_name": "slaughter blennoma overdure", "last_name": "ficoides furfuralcohol adroitly"}}, {"pk": 66, "model": "testapp.testperson", "fields": {"first_name": "frijol pressmanship ebrious", "last_name": "annelidian fenestrato swingable"}}, {"pk": 67, "model": "testapp.testperson", "fields": {"first_name": "besauce southwards cloudiness", "last_name": "malurinae hellhound romeshot"}}, {"pk": 68, "model": "testapp.testperson", "fields": {"first_name": "indemnitee tussilago cresol", "last_name": "airified pseudophilosophical sodwork"}}, {"pk": 69, "model": "testapp.testperson", "fields": {"first_name": "wincingly pennariidae angstrom", "last_name": "unassenting botanophile veuglaire"}}, {"pk": 70, "model": "testapp.testperson", "fields": {"first_name": "pharyngotonsillitis mustelinous chrysazol", "last_name": "streamhead acatastasia tentaclelike"}}, {"pk": 71, "model": "testapp.testperson", "fields": {"first_name": "counteraccusation whulter dioxane", "last_name": "mandarinate delegable thermopolypneic"}}, {"pk": 72, "model": "testapp.testperson", "fields": {"first_name": "ropelayer sportswoman impugnable", "last_name": "archimedes antitypy salpingopalatal"}}, {"pk": 73, "model": "testapp.testperson", "fields": {"first_name": "osteoglossoid preknit amianth", "last_name": "ungreatly sarmatic hoedown"}}, {"pk": 74, "model": "testapp.testperson", "fields": {"first_name": "olfactometric citification outbox", "last_name": "kidneywort slimy urinant"}}, {"pk": 75, "model": "testapp.testperson", "fields": {"first_name": "semic debtee ringtaw", "last_name": "geodynamical zoocytial pitangua"}}, {"pk": 76, "model": "testapp.testperson", "fields": {"first_name": "scornful alkali compunctionary", "last_name": "disforest motivity monodic"}}, {"pk": 77, "model": "testapp.testperson", "fields": {"first_name": "amortizement erg scaphites", "last_name": "bye vibrissa behooving"}}, {"pk": 78, "model": "testapp.testperson", "fields": {"first_name": "balboa nonextensional ruin", "last_name": "proinvestment cuscus lysidine"}}, {"pk": 79, "model": "testapp.testperson", "fields": {"first_name": "actinoblast forename antimodel", "last_name": "shotbush amanist nerveroot"}}, {"pk": 80, "model": "testapp.testperson", "fields": {"first_name": "homiletics stereotomical concaveness", "last_name": "submicron asystolism quintic"}}, {"pk": 81, "model": "testapp.testperson", "fields": {"first_name": "prefulfill seeingly unelevated", "last_name": "engarble existential clathrarian"}}, {"pk": 82, "model": "testapp.testperson", "fields": {"first_name": "decarbonize adrenalone adopter", "last_name": "automatin tosephta necturus"}}, {"pk": 83, "model": "testapp.testperson", "fields": {"first_name": "chlorioninae therapeutically beglerbeg", "last_name": "subproctor kinetogenetic ambrosian"}}, {"pk": 84, "model": "testapp.testperson", "fields": {"first_name": "staggers unsparable arzrunite", "last_name": "deduction outbring uncompulsory"}}, {"pk": 85, "model": "testapp.testperson", "fields": {"first_name": "whipcord maypoling translay", "last_name": "nulliplex premotion blinkard"}}, {"pk": 86, "model": "testapp.testperson", "fields": {"first_name": "preindispose uparna nonius", "last_name": "neogenetic despondency dilambdodont"}}, {"pk": 87, "model": "testapp.testperson", "fields": {"first_name": "winddog placentitis readjustable", "last_name": "isohemopyrrole cystoproctostomy spunny"}}, {"pk": 88, "model": "testapp.testperson", "fields": {"first_name": "zeuglodontidae antimetropic huaracho", "last_name": "endostylar politzerize plenum"}}, {"pk": 89, "model": "testapp.testperson", "fields": {"first_name": "roading empirism solymaean", "last_name": "nasoorbital ellipsone planetesimal"}}, {"pk": 90, "model": "testapp.testperson", "fields": {"first_name": "nonplacet lackadaisicalness thone", "last_name": "unprofessing effectively keened"}}, {"pk": 91, "model": "testapp.testperson", "fields": {"first_name": "belittler extrapolator orchitic", "last_name": "metaplast centetidae momental"}}, {"pk": 92, "model": "testapp.testperson", "fields": {"first_name": "yule remantle disastimeter", "last_name": "trophism sweeping bovarysm"}}, {"pk": 93, "model": "testapp.testperson", "fields": {"first_name": "flaser ungroaning perduringly", "last_name": "intone corrugate writing"}}, {"pk": 94, "model": "testapp.testperson", "fields": {"first_name": "authenticator elderberry birimose", "last_name": "buzzgloak abjectedness isogoniostat"}}, {"pk": 95, "model": "testapp.testperson", "fields": {"first_name": "hypermorph erastianism typocosmy", "last_name": "reassimilate neobeckia undeclinableness"}}, {"pk": 96, "model": "testapp.testperson", "fields": {"first_name": "imbrication reversive anosmatic", "last_name": "hospitize merogastrula ossicle"}}, {"pk": 97, "model": "testapp.testperson", "fields": {"first_name": "cocurrent downlying preconsolidation", "last_name": "patchwork unsolvable pulverulently"}}, {"pk": 98, "model": "testapp.testperson", "fields": {"first_name": "mechanolater rodolphus uncompassionated", "last_name": "professor salutiferous baste"}}, {"pk": 99, "model": "testapp.testperson", "fields": {"first_name": "talliate woodenly waterbosh", "last_name": "aion maladministration anacardiaceae"}}, {"pk": 100, "model": "testapp.testperson", "fields": {"first_name": "partitionment coexistence schoolable", "last_name": "quercitannin undertime drawspring"}}]